Workbook

Sheet INSTRUCCIONES
A1: Diagnóstico Integral IDEAS – Guía de uso
A3: Objetivo | B3: Diagnosticar el nivel de madurez de la empresa para identificar brechas, riesgos y oportunidades de servicio para IDEAS.
A4: Cómo usar | B4: Completar la hoja DIAGNOSTICO. En PUNTAJE sólo se permite 0, 1, 2, 3 o 4. La hoja SCORING Y RESULTADOS y el DASHBOARD se actualizan automáticamente.
A5: Tiempo sugerido | B5: 3 a 4 horas de entrevista con referentes de cada área.
A6: Interpretación del puntaje | B6: 0 = Inexistente | 1 = Inicial | 2 = Parcial | 3 = Implementado | 4 = Estandarizado
A7: Regla de evidencia | B7: Si la empresa dice que lo hace pero no muestra evidencia, no debería superar 2 puntos.
A8: Críticas | B8: Las preguntas marcadas como CRÍTICA = SI impactan el score ajustado si obtienen puntaje menor a 2.
A10: Escala de evaluación
A11: ESCALA | B11: NIVEL | C11: DESCRIPCIÓN GENERAL | D11: CRITERIO DOCUMENTAL | E11: CRITERIO OPERATIVO | F11: CRITERIO DE CONTROL | G11: RIESGO SI ES CRÍTICA
A12: 0 | B12: Inexistente | C12: No existe práctica formal ni evidencia | D12: No hay documento ni registro | E12: No se realiza la actividad | F12: No existe medición ni control | G12: Riesgo Muy Alto
A13: 1 | B13: Inicial | C13: Existe informalmente o depende de personas | D13: Puede haber información verbal o documento aislado | E13: Se realiza ocasionalmente sin sistemática | F13: No se mide ni analiza | G13: Riesgo Alto
A14: 2 | B14: Parcial | C14: Existe definido pero se aplica de forma inconsistente | D14: Hay documento pero no siempre actualizado | E14: Se ejecuta parcialmente o sin disciplina | F14: Se controla de manera reactiva | G14: Riesgo Medio
A15: 3 | B15: Implementado | C15: Está definido y se aplica regularmente | D15: Documentación vigente disponible | E15: Se ejecuta de manera sistemática | F15: Se registran resultados y se analizan | G15: Riesgo Bajo
A16: 4 | B16: Estandarizado | C16: Está sistematizado y mejora continuamente | D16: Documentado, controlado y actualizado | E16: Se aplica consistentemente en toda la organización | F16: Se mide, analiza y mejora con indicadores | G16: Riesgo Muy Bajo

Sheet DIAGNOSTICO
A1: EJE | B1: AREA | C1: CODIGO | D1: TIPO | E1: CRITICA | F1: PREGUNTA | G1: RESPONSABLE | H1: PUNTAJE (0-4) | I1: EVIDENCIA | J1: OBSERVACIONES IDEAS
A2: Dirección y Estrategia | B2: Dirección | C2: D-01 | D2: C | E2: SI | F2: ¿Existe una planificación anual formal definida por la dirección?
A3: Dirección y Estrategia | B3: Dirección | C3: D-02 | D3: C | E3: SI | F3: ¿Se realiza un seguimiento periódico de los resultados del negocio?
A4: Dirección y Estrategia | B4: Dirección | C4: D-03 | D4: C | E4: NO | F4: ¿Se identifican y analizan los riesgos principales del negocio?
A5: Dirección y Estrategia | B5: Dirección | C5: D-04 | D5: P | E5: NO | F5: ¿Existe un plan estratégico a mediano plazo (2–3 años)?
A6: Dirección y Estrategia | B6: Dirección | C6: D-05 | D6: P | E6: NO | F6: ¿Las decisiones se toman en base a indicadores o datos concretos?
A7: Dirección y Estrategia | B7: Dirección | C7: D-06 | D7: C | E7: NO | F7: ¿Se realiza una revisión estructurada de la gestión (tipo comité o dirección)?
A8: Organización | B8: Estructura | C8: O-01 | D8: C | E8: NO | F8: ¿Existe un organigrama formal y actualizado?
A9: Organización | B9: Estructura | C9: O-02 | D9: C | E9: SI | F9: ¿Están claramente definidas las responsabilidades de cada puesto?
A10: Organización | B10: Estructura | C10: O-03 | D10: C | E10: NO | F10: ¿Existen descripciones de puesto documentadas?
A11: Organización | B11: Estructura | C11: O-04 | D11: P | E11: NO | F11: ¿Está definida la autoridad y toma de decisiones en cada nivel?
A12: Organización | B12: Estructura | C12: O-05 | D12: C | E12: NO | F12: ¿Se realizan reuniones de gestión con agenda y seguimiento?
A13: Mapa de Procesos | B13: Procesos | C13: MP-01 | D13: C | E13: SI | F13: ¿Existe un mapa de procesos formal de la organización?
... A87: Logística y Almacenes | B87: Logística | C87: LO-10 | D87: P | E87: NO | F87: ¿Existe planificación de abastecimiento alineada a producción?

Sheet SCORING Y RESULTADOS
A1: Scoring por eje
A2: EJE | B2: PROMEDIO EJE | C2: PESO % | D2: SCORE PONDERADO | E2: BRECHA % | F2: CRÍTICAS <2 | G2: ALERTA
A3: Dirección y Estrategia | B3: =IFERROR(AVERAGEIF(DIAGNOSTICO!$A:$A,A3,DIAGNOSTICO!$H:$H),0) -> 0 | C3: 8 | D3: =B3*C3/100 -> 0 | E3: =(4-B3)/4*100 -> 100 | F3: =COUNTIFS(DIAGNOSTICO!$A:$A,A3,DIAGNOSTICO!$E:$E,"SI",DIAGNOSTICO!$H:$H,"<>",DIAGNOSTICO!$H:$H,"<2") -> 0 | G3: =IF(F3>0,"ALERTA ROJA","OK") -> OK
A4: Organización | B4: =IFERROR(AVERAGEIF(DIAGNOSTICO!$A:$A,A4,DIAGNOSTICO!$H:$H),0) -> 0 | C4: 6 | D4: =B4*C4/100 -> 0 | E4: =(4-B4)/4*100 -> 100 | F4: =COUNTIFS(DIAGNOSTICO!$A:$A,A4,DIAGNOSTICO!$E:$E,"SI",DIAGNOSTICO!$H:$H,"<>",DIAGNOSTICO!$H:$H,"<2") -> 0 | G4: =IF(F4>0,"ALERTA ROJA","OK") -> OK
A5: Mapa de Procesos | B5: =IFERROR(AVERAGEIF(DIAGNOSTICO!$A:$A,A5,DIAGNOSTICO!$H:$H),0) -> 0 | C5: 8 | D5: =B5*C5/100 -> 0 | E5: =(4-B5)/4*100 -> 100 | F5: =COUNTIFS(DIAGNOSTICO!$A:$A,A5,DIAGNOSTICO!$E:$E,"SI",DIAGNOSTICO!$H:$H,"<>",DIAGNOSTICO!$H:$H,"<2") -> 0 | G5: =IF(F5>0,"ALERTA ROJA","OK") -> OK
A6: Producción | B6: =IFERROR(AVERAGEIF(DIAGNOSTICO!$A:$A,A6,DIAGNOSTICO!$H:$H),0) -> 0 | C6: 15 | D6: =B6*C6/100 -> 0 | E6: =(4-B6)/4*100 -> 100 | F6: =COUNTIFS(DIAGNOSTICO!$A:$A,A6,DIAGNOSTICO!$E:$E,"SI",DIAGNOSTICO!$H:$H,"<>",DIAGNOSTICO!$H:$H,"<2") -> 0 | G6: =IF(F6>0,"ALERTA ROJA","OK") -> OK
A7: Mantenimiento | B7: =IFERROR(AVERAGEIF(DIAGNOSTICO!$A:$A,A7,DIAGNOSTICO!$H:$H),0) -> 0 | C7: 10 | D7: =B7*C7/100 -> 0 | E7: =(4-B7)/4*100 -> 100 | F7: =COUNTIFS(DIAGNOSTICO!$A:$A,A7,DIAGNOSTICO!$E:$E,"SI",DIAGNOSTICO!$H:$H,"<>",DIAGNOSTICO!$H:$H,"<2") -> 0 | G7: =IF(F7>0,"ALERTA ROJA","OK") -> OK
A8: Calidad | B8: =IFERROR(AVERAGEIF(DIAGNOSTICO!$A:$A,A8,DIAGNOSTICO!$H:$H),0) -> 0 | C8: 15 | D8: =B8*C8/100 -> 0 | E8: =(4-B8)/4*100 -> 100 | F8: =COUNTIFS(DIAGNOSTICO!$A:$A,A8,DIAGNOSTICO!$E:$E,"SI",DIAGNOSTICO!$H:$H,"<>",DIAGNOSTICO!$H:$H,"<2") -> 0 | G8: =IF(F8>0,"ALERTA ROJA","OK") -> OK
A9: Compras | B9: =IFERROR(AVERAGEIF(DIAGNOSTICO!$A:$A,A9,DIAGNOSTICO!$H:$H),0) -> 0 | C9: 6 | D9: =B9*C9/100 -> 0 | E9: =(4-B9)/4*100 -> 100 | F9: =COUNTIFS(DIAGNOSTICO!$A:$A,A9,DIAGNOSTICO!$E:$E,"SI",DIAGNOSTICO!$H:$H,"<>",DIAGNOSTICO!$H:$H,"<2") -> 0 | G9: =IF(F9>0,"ALERTA ROJA","OK") -> OK
A10: Comercial | B10: =IFERROR(AVERAGEIF(DIAGNOSTICO!$A:$A,A10,DIAGNOSTICO!$H:$H),0) -> 0 | C10: 5 | D10: =B10*C10/100 -> 0 | E10: =(4-B10)/4*100 -> 100 | F10: =COUNTIFS(DIAGNOSTICO!$A:$A,A10,DIAGNOSTICO!$E:$E,"SI",DIAGNOSTICO!$H:$H,"<>",DIAGNOSTICO!$H:$H,"<2") -> 0 | G10: =IF(F10>0,"ALERTA ROJA","OK") -> OK
A11: Finanzas | B11: =IFERROR(AVERAGEIF(DIAGNOSTICO!$A:$A,A11,DIAGNOSTICO!$H:$H),0) -> 0 | C11: 10 | D11: =B11*C11/100 -> 0 | E11: =(4-B11)/4*100 -> 100 | F11: =COUNTIFS(DIAGNOSTICO!$A:$A,A11,DIAGNOSTICO!$E:$E,"SI",DIAGNOSTICO!$H:$H,"<>",DIAGNOSTICO!$H:$H,"<2") -> 0 | G11: =IF(F11>0,"ALERTA ROJA","OK") -> OK
A12: Seguridad y Salud | B12: =IFERROR(AVERAGEIF(DIAGNOSTICO!$A:$A,A12,DIAGNOSTICO!$H:$H),0) -> 0 | C12: 7 | D12: =B12*C12/100 -> 0 | E12: =(4-B12)/4*100 -> 100 | F12: =COUNTIFS(DIAGNOSTICO!$A:$A,A12,DIAGNOSTICO!$E:$E,"SI",DIAGNOSTICO!$H:$H,"<>",DIAGNOSTICO!$H:$H,"<2") -> 0 | G12: =IF(F12>0,"ALERTA ROJA","OK") -> OK
A13: Ambiental | B13: =IFERROR(AVERAGEIF(DIAGNOSTICO!$A:$A,A13,DIAGNOSTICO!$H:$H),0) -> 0 | C13: 5 | D13: =B13*C13/100 -> 0 | E13: =(4-B13)/4*100 -> 100 | F13: =COUNTIFS(DIAGNOSTICO!$A:$A,A13,DIAGNOSTICO!$E:$E,"SI",DIAGNOSTICO!$H:$H,"<>",DIAGNOSTICO!$H:$H,"<2") -> 0 | G13: =IF(F13>0,"ALERTA ROJA","OK") -> OK
A14: Riesgos y Continuidad | B14: =IFERROR(AVERAGEIF(DIAGNOSTICO!$A:$A,A14,DIAGNOSTICO!$H:$H),0) -> 0 | C14: 3 | D14: =B14*C14/100 -> 0 | E14: =(4-B14)/4*100 -> 100 | F14: =COUNTIFS(DIAGNOSTICO!$A:$A,A14,DIAGNOSTICO!$E:$E,"SI",DIAGNOSTICO!$H:$H,"<>",DIAGNOSTICO!$H:$H,"<2") -> 0 | G14: =IF(F14>0,"ALERTA ROJA","OK") -> OK
... A16: Logística y Almacenes | B16: =IFERROR(AVERAGEIF(DIAGNOSTICO!$A:$A,A16,DIAGNOSTICO!$H:$H),0) -> 0 | C16: 10 | D16: =B16*C16/100 -> 0 | E16: =(4-B16)/4*100 -> 100 | F16: =COUNTIFS(DIAGNOSTICO!$A:$A,A16,DIAGNOSTICO!$E:$E,"SI",DIAGNOSTICO!$H:$H,"<>",DIAGNOSTICO!$H:$H,"<2") -> 0 | G16: =IF(F16>0,"ALERTA ROJA","OK") -> OK
A19: INDICADOR GLOBAL | B19: VALOR
A20: Preguntas Respondidas | B20: =COUNT(DIAGNOSTICO!$H:$H) -> 0
A21: Avance de carga % | B21: =ROUND(B20/86*100,1) -> 0
A22: Cantidad Total Críticas <2 | B22: =SUM(F3:F16) -> 0
A23: Score Global (0-4) | B23: =SUM(D3:D16) -> 0
A24: Score Global % | B24: =ROUND(B23/4*100,1) -> 0
A25: Score Ajustado % | B25: =IF(B22=0,B24,IF(B22<=2,B24*0.95,IF(B22<=5,B24*0.9,B24*0.85))) -> 0
A26: Nivel Global | B26: =IF(B20=0,"Sin datos",IF(B25<25,"Crítico",IF(B25<50,"Básico",IF(B25<70,"Intermedio",IF(B25<85,"Controlado","Robusto"))))) -> Sin datos
A27: Semáforo | B27: =IF(B20=0,"Pendiente",IF(B25<50,"Riesgo Alto",IF(B25<70,"Riesgo Medio","Controlado"))) -> Pendiente

Sheet DASHBOARD
A1: Dashboard Ejecutivo – Diagnóstico Integral IDEAS
A2: Score Ajustado % | D2: Nivel Global | G2: Críticas Activas | J2: Semáforo
A3: ='SCORING Y RESULTADOS'!B25 -> 0 | D3: ='SCORING Y RESULTADOS'!B26 -> Sin datos | G3: ='SCORING Y RESULTADOS'!B22 -> 0 | J3: ='SCORING Y RESULTADOS'!B27 -> Pendiente
A22: EJE | B22: PROMEDIO | C22: BRECHA %
A23: ='SCORING Y RESULTADOS'!A3 -> Dirección y Estrategia | B23: ='SCORING Y RESULTADOS'!B3 -> 0 | C23: ='SCORING Y RESULTADOS'!E3 -> 100
A24: ='SCORING Y RESULTADOS'!A4 -> Organización | B24: ='SCORING Y RESULTADOS'!B4 -> 0 | C24: ='SCORING Y RESULTADOS'!E4 -> 100
A25: ='SCORING Y RESULTADOS'!A5 -> Mapa de Procesos | B25: ='SCORING Y RESULTADOS'!B5 -> 0 | C25: ='SCORING Y RESULTADOS'!E5 -> 100
A26: ='SCORING Y RESULTADOS'!A6 -> Producción | B26: ='SCORING Y RESULTADOS'!B6 -> 0 | C26: ='SCORING Y RESULTADOS'!E6 -> 100
A27: ='SCORING Y RESULTADOS'!A7 -> Mantenimiento | B27: ='SCORING Y RESULTADOS'!B7 -> 0 | C27: ='SCORING Y RESULTADOS'!E7 -> 100
A28: ='SCORING Y RESULTADOS'!A8 -> Calidad | B28: ='SCORING Y RESULTADOS'!B8 -> 0 | C28: ='SCORING Y RESULTADOS'!E8 -> 100
A29: ='SCORING Y RESULTADOS'!A9 -> Compras | B29: ='SCORING Y RESULTADOS'!B9 -> 0 | C29: ='SCORING Y RESULTADOS'!E9 -> 100
A30: ='SCORING Y RESULTADOS'!A10 -> Comercial | B30: ='SCORING Y RESULTADOS'!B10 -> 0 | C30: ='SCORING Y RESULTADOS'!E10 -> 100
A31: ='SCORING Y RESULTADOS'!A11 -> Finanzas | B31: ='SCORING Y RESULTADOS'!B11 -> 0 | C31: ='SCORING Y RESULTADOS'!E11 -> 100
A32: ='SCORING Y RESULTADOS'!A12 -> Seguridad y Salud | B32: ='SCORING Y RESULTADOS'!B12 -> 0 | C32: ='SCORING Y RESULTADOS'!E12 -> 100
A33: ='SCORING Y RESULTADOS'!A13 -> Ambiental | B33: ='SCORING Y RESULTADOS'!B13 -> 0 | C33: ='SCORING Y RESULTADOS'!E13 -> 100
A34: ='SCORING Y RESULTADOS'!A14 -> Riesgos y Continuidad | B34: ='SCORING Y RESULTADOS'!B14 -> 0 | C34: ='SCORING Y RESULTADOS'!E14 -> 100
... A36: ='SCORING Y RESULTADOS'!A16 -> Logística y Almacenes | B36: ='SCORING Y RESULTADOS'!B16 -> 0 | C36: ='SCORING Y RESULTADOS'!E16 -> 100
A38: Conclusión ejecutiva
A39: =IF('SCORING Y RESULTADOS'!B20=0,"Pendiente de carga: completar puntajes en la hoja DIAGNOSTICO para habilitar el resultado ejecutivo.",IF('SCORING Y RESULTADOS'!B25<50,"La organización presenta un nivel de madurez bajo, con riesgos estructurales significativos y " & 'SCORING Y RESULTADOS'!B22 & " áreas críticas que requieren intervención prioritaria.",IF('SCORING Y RESULTADOS'!B25<70,"La organización posee una base de gestión definida, aunque presenta oportunidades relevantes de mejora y " & 'SCORING Y RESULTADOS'!B22 & " riesgos críticos que impactan su estabilidad operativa.",IF('SCORING Y RESULTADOS'!B25<85,"La organización se encuentra en un nivel controlado, con estructura funcional y oportunidades puntuales de optimización.","La organización presenta un sistema robusto y controlado, con oportunidades de mejora estratégica.")))) -> Pendiente de carga: completar puntajes en la hoja DIAGNOSTICO para habilitar el resultado ejecutivo.
A44: Comentarios del consultor

Sheet CRITERIOS DE EVALUACION
A1: ESCALA | B1: NIVEL | C1: DESCRIPCION GENERAL | D1: CRITERIO DOCUMENTAL | E1: CRITERIO OPERATIVO | F1: CRITERIO DE CONTROL | G1: NIVEL DE RIESGO (SI ES CRITICA)
A2: 0 | B2: Inexistente | C2: No existe práctica formal ni evidencia | D2: No hay documento ni registro | E2: No se realiza la actividad | F2: No existe medición ni control | G2: Riesgo Muy Alto
A3: 1 | B3: Inicial | C3: Existe informalmente o depende de personas | D3: Puede haber información verbal o documento aislado | E3: Se realiza ocasionalmente sin sistemática | F3: No se mide ni analiza | G3: Riesgo Alto
A4: 2 | B4: Parcial | C4: Existe definido pero se aplica de forma inconsistente | D4: Hay documento pero no siempre actualizado | E4: Se ejecuta parcialmente o sin disciplina | F4: Se controla de manera reactiva | G4: Riesgo Medio
A5: 3 | B5: Implementado | C5: Está definido y se aplica regularmente | D5: Documentación vigente disponible | E5: Se ejecuta de manera sistemática | F5: Se registran resultados y se analizan | G5: Riesgo Bajo
A6: 4 | B6: Estandarizado | C6: Está sistematizado y mejora continuamente | D6: Documentado, controlado y actualizado | E6: Se aplica consistentemente en toda la organización | F6: Se mide, analiza y mejora con indicadores | G6: Riesgo Muy Bajo
A8: PUNTAJE OBTENIDO | B8: NIVEL DE ALERTA | C8: ACCION RECOMENDADA
A9: 0 | B9: Alerta Roja | C9: Intervención inmediata requerida
A10: 1 | B10: Riesgo Alto | C10: Plan de acción prioritario (0-90 días)
A11: 2 | B11: Riesgo Medio | C11: Plan de mejora estructurado
A12: 3 | B12: Controlado | C12: Seguimiento periódico
A13: 4 | B13: Óptimo | C13: Mantener y mejorar
A15: PROMEDIO POR EJE | B15: NIVEL DE MADUREZ | C15: INTERPRETACION
A16: 0 - 1.4 | B16: Crítico | C16: Sistema inexistente o fuera de control
A17: 1.5 - 2.4 | B17: Básico | C17: Gestión reactiva y poco estructurada
A18: 2.5 - 3.2 | B18: Intermedio | C18: Gestión definida pero con oportunidades claras
A19: 3.3 - 3.7 | B19: Controlado | C19: Gestión estable y predecible
A20: 3.8 - 4.0 | B20: Robusto | C20: Gestión madura y optimizada
